<Properties StartupConfiguration="{447DE43A-143F-28FD-1D58-64C2F968112C}|">
  <MonoDevelop.Ide.Workbench ActiveDocument="Assets/Scripts/QuitGame.cs">
    <Files>
      <File FileName="Assets/Scripts/QuitGame.cs" Line="13" Column="1" />
    </Files>
  </MonoDevelop.Ide.Workbench>
  <MonoDevelop.Ide.DebuggingService.PinnedWatches />
  <MonoDevelop.Ide.Workspace ActiveConfiguration="Debug" />
  <MonoDevelop.Ide.ItemProperties.Assembly-CSharp PreferredExecutionTarget="3922dc4a-cc37-4680-af30-7cde81726cd5" />
  <MonoDevelop.Ide.DebuggingService.Breakpoints>
    <BreakpointStore />
  </MonoDevelop.Ide.DebuggingService.Breakpoints>
  <MultiItemStartupConfigurations />
</Properties>